{
    "Role": "Backend Developer",
    "fundamentals": [
        {"skill": "C#", "category": "Programming Languages"},
        {"skill": "Git", "category": "Version Control Systems"},
        {"skill": "POSIX Basics", "category": "Terminal Usage"},
        {"skill": "PostgreSQL", "category": "Databases"},
        {"skill": "Redis", "category": "Caching"},
        {"skill": "Nginx", "category": "Web Servers"},
        {"skill": "Docker", "category": "Containerization"},
        {"skill": "Java", "category": "Programming Languages"},
        {"skill": "JavaScript", "category": "Programming Languages"},
        {"skill": "GitHub", "category": "Version Control Systems"},
        {"skill": "MySQL", "category": "Databases"},
        {"skill": "Elasticsearch", "category": "Search Engines"},
        {"skill": "Kubernetes", "category": "Containerization"},
        {"skill": "RabbitMQ", "category": "Message Brokers"},
        {"skill": "Python", "category": "Programming Languages"},
        {"skill": "PHP", "category": "Programming Languages"},
        {"skill": "Ruby", "category": "Programming Languages"},
        {"skill": "GitLab", "category": "Version Control Systems"},
        {"skill": "Bitbucket", "category": "Version Control Systems"},
        {"skill": "stdin, stdout, stderr, pipes", "category": "Terminal Usage"},
        {"skill": "Basic Terminal Commands", "category": "Terminal Usage"},
        {"skill": "MS SQL", "category": "Databases"},
        {"skill": "Oracle", "category": "Databases"},
        {"skill": "Firebase Realtime", "category": "Databases"},
        {"skill": "HBase", "category": "Databases"},
        {"skill": "Graph DBs", "category": "Databases"},
        {"skill": "Neo4j", "category": "Databases"},
        {"skill": "DynamoDB", "category": "Databases"},
        {"skill": "Column DBs", "category": "Databases"},
        {"skill": "Cassandra", "category": "Databases"},
        {"skill": "RethinkDB", "category": "Databases"},
        {"skill": "Document DBs", "category": "Databases"},
        {"skill": "MongoDB", "category": "Databases"},
        {"skill": "CouchDB", "category": "Databases"},
        {"skill": "ACID", "category": "Database Concepts"},
        {"skill": "N+1 Problem", "category": "Database Concepts"},
        {"skill": "Normalization", "category": "Database Concepts"},
        {"skill": "Failure Modes", "category": "Database Concepts"},
        {"skill": "Data Replication", "category": "Database Concepts"},
        {"skill": "Database Indexes", "category": "Database Concepts"},
        {"skill": "Scaling Databases", "category": "Database Concepts"},
        {"skill": "Transactions", "category": "Database Concepts"},
        {"skill": "Memory Management", "category": "Operating Systems and General Knowledge"},
        {"skill": "Threads and Concurrency", "category": "Operating Systems and General Knowledge"},
        {"skill": "Process Management", "category": "Operating Systems and General Knowledge"},
        {"skill": "I/O Management", "category": "Operating Systems and General Knowledge"},
        {"skill": "Interprocess Communication", "category": "Operating Systems and General Knowledge"},
        {"skill": "How OSs work in General", "category": "Operating Systems and General Knowledge"},
        {"skill": "Open API Specs", "category": "API Design"},
        {"skill": "REST", "category": "API Design"},
        {"skill": "JSON APIs", "category": "API Design"},
        {"skill": "gRPC", "category": "API Design"},
        {"skill": "GraphQL", "category": "API Design"},
        {"skill": "HATEOAS", "category": "API Design"},
        {"skill": "Authentication", "category": "Authentication and Security"},
        {"skill": "OpenID", "category": "Authentication and Security"},
        {"skill": "SAML", "category": "Authentication and Security"},
        {"skill": "OAuth", "category": "Authentication and Security"},
        {"skill": "JWT", "category": "Authentication and Security"},
        {"skill": "HTTPS", "category": "Authentication and Security"},
        {"skill": "SSL/TLS", "category": "Authentication and Security"},
        {"skill": "Content Security Policy", "category": "Authentication and Security"},
        {"skill": "OWASP Risks", "category": "Authentication and Security"},
        {"skill": "CORS", "category": "Authentication and Security"}
    ],
    "intermediate": [
        {"skill": "Rust", "category": "Programming Languages"},
        {"skill": "Go", "category": "Programming Languages"},
        {"skill": "Integration Testing", "category": "Testing"},
        {"skill": "Unit Testing", "category": "Testing"},
        {"skill": "Functional Testing", "category": "Testing"},
        {"skill": "CI/CD", "category": "Testing"},
        {"skill": "Solr", "category": "Search Engines"},
        {"skill": "Apache", "category": "Web Servers"},
        {"skill": "Caddy", "category": "Web Servers"},
        {"skill": "MS IIS", "category": "Web Servers"},
        {"skill": "Microservices", "category": "Architecture"},
        {"skill": "SOA", "category": "Architecture"},
        {"skill": "Serverless", "category": "Architecture"},
        {"skill": "Service Mesh", "category": "Architecture"},
        {"skill": "Twelve Factor Apps", "category": "Architecture"},
        {"skill": "Monolithic Apps", "category": "Architecture"},
        {"skill": "GOF Design Patterns", "category": "Architecture"},
        {"skill": "Architectural Patterns", "category": "Architecture"},
        {"skill": "Domain Driven Design", "category": "Architecture"},
        {"skill": "Test Driven Development", "category": "Architecture"},
        {"skill": "CQRS", "category": "Architecture"},
        {"skill": "Event Sourcing", "category": "Architecture"},
        {"skill": "Kafka", "category": "Message Brokers"},
        {"skill": "LXC", "category": "Containerization"},
        {"skill": "Containerization vs Virtualization", "category": "Containerization"},
        {"skill": "Web Security Knowledge", "category": "Authentication and Security"}
    ],
    "expert": [
        {"skill": "GraphQL", "category": "GraphQL Ecosystem"},
        {"skill": "Apollo", "category": "GraphQL Ecosystem"},
        {"skill": "Relay Modern", "category": "GraphQL Ecosystem"},
        {"skill": "CDN", "category": "Scaling and Performance"},
        {"skill": "Sharding Strategies", "category": "Scaling and Performance"},
        {"skill": "CAP Theorem", "category": "Scaling and Performance"},
        {"skill": "Graceful Degradation", "category": "Scaling and Performance"},
        {"skill": "Throttling", "category": "Scaling and Performance"},
        {"skill": "Backpressure", "category": "Scaling and Performance"},
        {"skill": "Loadshifting", "category": "Scaling and Performance"},
        {"skill": "Building for Scale", "category": "Scaling and Performance"},
        {"skill": "Instrumentation", "category": "Monitoring and Observability"},
        {"skill": "Monitoring", "category": "Monitoring and Observability"},
        {"skill": "Circuit Breaker", "category": "Monitoring and Observability"},
        {"skill": "Mitigation Strategies", "category": "Monitoring and Observability"},
        {"skill": "Telemetry", "category": "Monitoring and Observability"},
        {"skill": "Types of Scaling", "category": "Monitoring and Observability"},
        {"skill": "Observability", "category": "Monitoring and Observability"},
        {"skill": "Metrics logging", "category": "Monitoring and Observability"},
        {"skill": "DevOps Roadmap", "category": "DevOps Integration"}
    ]
}
